coupml/__init__.py
coupml/actions.py
coupml/constants.py
coupml/dealer.py
coupml/game.py
coupml/observer.py
coupml/player.py
coupml/rule_ai.py
coupml/utils.py
coupml/view.py
coupml-0.1.1.dist-info/LICENSE
coupml-0.1.1.dist-info/METADATA
coupml-0.1.1.dist-info/WHEEL
coupml-0.1.1.dist-info/top_level.txt
coupml-0.1.1.dist-info/RECORD
