Metadata-Version: 2.1
Name: coupml
Version: 0.1.1
Summary: An implementation of the card game Coup intended for machine learning
Author-email: Chris Brown <chris@thebrown.net>
License: Copyright 2023 Chris Brown
Project-URL: Homepage, https://github.com/octachrome/coupml
License-File: LICENSE
Provides-Extra: dev
Requires-Dist: numpy ; extra == 'dev'
Requires-Dist: transcrypt ; extra == 'dev'
